gitonic/__init__.py
gitonic/__main__.py
gitonic/gitonic.py
gitonic/gtcd.py
gitonic/gtcommon.py
gitonic/gtls.py
gitonic/core/__init__.py
gitonic/core/conf.py
gitonic/core/configs.py
gitonic/core/const.py
gitonic/core/dataflow.py
gitonic/core/file.py
gitonic/core/gitcmd.py
gitonic/core/githubver.py
gitonic/core/gitobj.py
gitonic/core/giton.py
gitonic/core/gitonapp.py
gitonic/core/gitutil.py
gitonic/core/logs.py
gitonic/core/proc.py
gitonic/core/runr.py
gitonic/core/sysutil.py
gitonic/core/task.py
gitonic/tkui/__init__.py
gitonic/tkui/icons.py
gitonic/tkui/material_fonts.py
gitonic/tkui/singleinstance.py
gitonic/tkui/tkuiapp.py
gitonic/tkui/tkuicore.py
gitonic/tkui/tkuiview.py
gitonic/tkui/tkuiwidg.py
gitonic/tkui/material_fonts/LICENSE
gitonic/tkui/material_fonts/MaterialSymbolsOutlined_5BFILL_GRAD_opsz_wght_5D.codepoints
gitonic/tkui/material_fonts/MaterialSymbolsOutlined_5BFILL_GRAD_opsz_wght_5D.ttf
gitonic/tkui/material_fonts/MaterialSymbolsRounded_5BFILL_GRAD_opsz_wght_5D.codepoints
gitonic/tkui/material_fonts/MaterialSymbolsRounded_5BFILL_GRAD_opsz_wght_5D.ttf
gitonic/tkui/otherdeps/LICENSE-gitonic
gitonic/tkui/otherdeps/LICENSE-tktootip
gitonic-0.18.5.dist-info/licenses/LICENSE.md
gitonic-0.18.5.dist-info/METADATA
gitonic-0.18.5.dist-info/WHEEL
gitonic-0.18.5.dist-info/entry_points.txt
gitonic-0.18.5.dist-info/top_level.txt
gitonic-0.18.5.dist-info/RECORD
