Metadata-Version: 2.4
Name: gitonic
Version: 0.18.5
Summary: manage a multi git workspace
Home-page: https://github.com/kr-g/gitonic
Author: k. goger
Author-email: k.r.goger+gitonic@gmail.com
License: AGPLv3+
Keywords: python utility shell git git-workspace tkinter
Classifier: Development Status :: 3 - Alpha
Classifier: Operating System :: POSIX :: Linux
Classifier: Environment :: Other Environment
Classifier: Intended Audience :: Developers
Classifier: Topic :: Utilities
Classifier: Topic :: Desktop Environment
Classifier: Topic :: Software Development :: Version Control :: Git
Classifier: Programming Language :: Python :: 3
Requires-Python: >=3.12
License-File: LICENSE.md
Requires-Dist: pillow
Requires-Dist: tkinter-tooltip
Requires-Dist: semver
Requires-Dist: urllib3
Provides-Extra: pep08
Requires-Dist: pycodestyle; extra == "pep08"
Requires-Dist: flake8; extra == "pep08"
Requires-Dist: autopep8; extra == "pep08"
Provides-Extra: pep08-black
Requires-Dist: pycodestyle; extra == "pep08-black"
Requires-Dist: flake8; extra == "pep08-black"
Requires-Dist: black; extra == "pep08-black"
Provides-Extra: pep08-full
Requires-Dist: pycodestyle; extra == "pep08-full"
Requires-Dist: flake8; extra == "pep08-full"
Requires-Dist: autopep8; extra == "pep08-full"
Requires-Dist: black; extra == "pep08-full"
Requires-Dist: yapf; extra == "pep08-full"
Provides-Extra: meld
Requires-Dist: meld; extra == "meld"
Provides-Extra: default
Requires-Dist: pycodestyle; extra == "default"
Requires-Dist: flake8; extra == "default"
Requires-Dist: autopep8; extra == "default"
Requires-Dist: meld; extra == "default"
Dynamic: author
Dynamic: author-email
Dynamic: home-page
Dynamic: license-file
Dynamic: requires-dist
Dynamic: requires-python
